LICENSE.txt
MANIFEST.in
README.rst
setup.py
docs/Makefile
docs/big_picture.rst
docs/common_mistakes.rst
docs/conf.py
docs/contributing.rst
docs/index.rst
docs/installation.rst
docs/messaging_overview.rst
docs/right_for_you.rst
docs/theater_overview.rst
docs/token_overview.rst
docs/api/actors.rst
docs/api/errors.rst
docs/api/forums.rst
docs/api/index.rst
docs/api/messages.rst
docs/api/multiplayer.rst
docs/api/quickstart.rst
docs/api/theater.rst
docs/api/tokens.rst
docs/api/world.rst
docs/demos/guess_my_number.rst
kxg/__init__.py
kxg/actors.py
kxg/errors.py
kxg/forums.py
kxg/messages.py
kxg/multiplayer.py
kxg/quickstart.py
kxg/theater.py
kxg/tokens.py
kxg.egg-info/PKG-INFO
kxg.egg-info/SOURCES.txt
kxg.egg-info/dependency_links.txt
kxg.egg-info/not-zip-safe
kxg.egg-info/requires.txt
kxg.egg-info/top_level.txt
tests/.20_test_tokens.py.swp
tests/.30_test_messaging.py.swp
tests/.coverage
tests/.coverage.thinkpad.851.697327
tests/.coveragerc
tests/.gitignore
tests/10_test_errors.py
tests/20_test_tokens.py
tests/30_test_messaging.py
tests/40_test_theaters.py
tests/dummy_game.py
tests/pylintrc
tests/pytest.ini
tests/run_tests.py
tests/test_helpers.py
tests/.cache/v/cache/lastfailed
tests/htmlcov/_home_kale_kxgames_libraries_kxg_kxg___init___py.html
tests/htmlcov/_home_kale_kxgames_libraries_kxg_kxg_actors_py.html
tests/htmlcov/_home_kale_kxgames_libraries_kxg_kxg_errors_py.html
tests/htmlcov/_home_kale_kxgames_libraries_kxg_kxg_forums_py.html
tests/htmlcov/_home_kale_kxgames_libraries_kxg_kxg_messages_py.html
tests/htmlcov/_home_kale_kxgames_libraries_kxg_kxg_multiplayer_py.html
tests/htmlcov/_home_kale_kxgames_libraries_kxg_kxg_quickstart_py.html
tests/htmlcov/_home_kale_kxgames_libraries_kxg_kxg_theater_py.html
tests/htmlcov/_home_kale_kxgames_libraries_kxg_kxg_tokens_py.html
tests/htmlcov/_home_kale_kxgames_libraries_kxg_kxg_world_py.html
tests/htmlcov/coverage_html.js
tests/htmlcov/index.html
tests/htmlcov/jquery.debounce.min.js
tests/htmlcov/jquery.hotkeys.js
tests/htmlcov/jquery.isonscreen.js
tests/htmlcov/jquery.min.js
tests/htmlcov/jquery.tablesorter.min.js
tests/htmlcov/keybd_closed.png
tests/htmlcov/keybd_open.png
