Metadata-Version: 1.1
Name: kxg
Version: 0.2.0
Summary: A multiplayer game engine.
Home-page: https://github.com/kxgames/kxg
Author: Kale Kundert and Alex Mitchell
Author-email: kale@thekunderts.net
License: MIT
Keywords: kxg
Platform: UNKNOWN
Classifier: Development Status :: 2 - Pre-Alpha
Classifier: Intended Audience :: Developers
Classifier: License :: OSI Approved :: MIT License
Classifier: Natural Language :: English
Classifier: Programming Language :: Python :: 3
Classifier: Topic :: Software Development :: Libraries
